LICENSE
MANIFEST.in
README.rst
passport.py
setup.py
passport.egg-info/PKG-INFO
passport.egg-info/SOURCES.txt
passport.egg-info/dependency_links.txt
passport.egg-info/entry_points.txt
passport.egg-info/requires.txt
passport.egg-info/top_level.txt
passport.egg-info/zip-safe