Metadata-Version: 1.1
Name: passport
Version: 0.1.1
Summary: Light weight configuration management using Consul
Home-page: https://github.com/gmr/passport
Author: Gavin M. Roy
Author-email: gavinmroy@gmail.com
License: Copyright (c) 2014 AWeber Communications
